yt_viewfinder/__init__.py
yt_viewfinder/core.py
yt_viewfinder-2024.1.1.dist-info/LICENSE
yt_viewfinder-2024.1.1.dist-info/METADATA
yt_viewfinder-2024.1.1.dist-info/WHEEL
yt_viewfinder-2024.1.1.dist-info/top_level.txt
yt_viewfinder-2024.1.1.dist-info/RECORD
