Metadata-Version: 2.1
Name: yt_viewfinder
Version: 2024.1.1
Summary: A Python package that fetches YouTube video view counts by video titles and optional artists using async http requests.
Author-email: Jaydin <JaydinFreemanWork@gmail.com>
License: MIT License
Requires-Python: >=3.8
License-File: LICENSE
Requires-Dist: aiohttp
